mitylib/__init__.py
mitylib/_version.py
mitylib/call.py
mitylib/commands.py
mitylib/merge.py
mitylib/normalise.py
mitylib/report.py
mitylib/util.py
mitylib/annot/anticodon_positions.csv
mitylib/annot/gtf_annotations.csv
mitylib/annot/haplotype_data.csv
mitylib/annot/haplotype_data.xlsx
mitylib/annot/mgrb_variants.csv
mitylib/annot/mito_dna_func_loc.csv
mitylib/annot/mitomap_panel_annotations.csv
mitylib/annot/mitomap_panel_annotations.csv~original
mitylib/annot/mitotip_score_fixed_del.csv
mitylib/annot/mitotip_score_fixed_del.csv~original
mitylib/reference/b37d5.genome
mitylib/reference/hg19.chrM.fa
mitylib/reference/hg19.chrM.fa.fai
mitylib/reference/hg19.dict
mitylib/reference/hg19.genome
mitylib/reference/hg38.chrM.fa
mitylib/reference/hg38.chrM.fa.fai
mitylib/reference/hg38.dict
mitylib/reference/hg38.genome
mitylib/reference/hs37d5.MT.fa
mitylib/reference/hs37d5.MT.fa.fai
mitylib/reference/hs37d5.dict
mitylib/reference/hs37d5.genome
mitylib/reference/mm10.chrM.fa
mitylib/reference/mm10.chrM.fa.fai
mitylib/reference/mm10.genome
mitywgs-0.4.0.data/scripts/mity
mitywgs-0.4.0.dist-info/LICENSE.txt
mitywgs-0.4.0.dist-info/METADATA
mitywgs-0.4.0.dist-info/WHEEL
mitywgs-0.4.0.dist-info/top_level.txt
mitywgs-0.4.0.dist-info/RECORD
