Metadata-Version: 2.1
Name: mitywgs
Version: 0.4.0
Summary: A sensitive Mitochondrial variant detection pipeline from WGS data
Home-page: https://github.com/KCCG/mity
Author: Clare Puttick
Author-email: clare.puttick@gmail.com
License: MIT
Project-URL: Documentation, https://github.com/KCCG/mity/
Project-URL: Source, https://github.com/KCCG/mity/
Project-URL: Funding, http://garvan.org.au/kccg
Keywords: mitochondrial DNA genomics variant SNV INDEL
Platform: UNKNOWN
Classifier: Development Status :: 4 - Beta
Classifier: Environment :: Console
Classifier: Environment :: MacOS X
Classifier: Intended Audience :: Science/Research
Classifier: Intended Audience :: Healthcare Industry
Classifier: License :: Free for non-commercial use
Classifier: Natural Language :: English
Classifier: Operating System :: MacOS
Classifier: Operating System :: POSIX
Classifier: Operating System :: Unix
Classifier: Programming Language :: Python :: 3.5
Classifier: Programming Language :: Python :: 3.6
Classifier: Programming Language :: Python :: 3.7
Classifier: Topic :: Scientific/Engineering :: Bio-Informatics
Requires-Python: >=3.5.4
Requires-Dist: pyvcf
Requires-Dist: pysam
Requires-Dist: pandas
Requires-Dist: xlsxwriter
Requires-Dist: pyfastx
Requires-Dist: scipy
